aionextpay/__init__.py
aionextpay/exceptions.py
aionextpay/nextpay.py
aionextpay-1.0.8.dist-info/LICENSE
aionextpay-1.0.8.dist-info/METADATA
aionextpay-1.0.8.dist-info/WHEEL
aionextpay-1.0.8.dist-info/top_level.txt
aionextpay-1.0.8.dist-info/RECORD
