Metadata-Version: 2.1
Name: aionextpay
Version: 1.0.8
Summary: An async library for requesting to the nextpay.org purchase gate way.
Author-email: Hadi Alipoor <hadi.alipoor.h2o@gmail.com>
License: GNU GENERAL PUBLIC LICENSE
Project-URL: Homepage, https://github.com/HadiH2o/AioNextPay
Project-URL: Bug Tracker, https://github.com/HadiH2o/AioNextPay/issues
Classifier: Programming Language :: Python :: 3
Classifier: License :: OSI Approved :: MIT License
Classifier: Operating System :: OS Independent
Requires-Python: >=3.7
License-File: LICENSE
Requires-Dist: aiohttp
